Workbook

Sheet Comece aqui
A1: FLOWO · MATERIAL PRÁTICO
A2: Planilha de precificação de serviços
A3: Organize custos, capacidade e margem para tomar decisões de preço com mais clareza.
A4: Veja o resumo na próxima aba. Depois, preencha somente as células rosadas e volte ao resumo para decidir o que fazer.
A6: 01 | C6: 02 | E6: 03
A7: Troque os custos e as horas de atendimento pelos números da barbearia. | C7: Revise material usado e tempo de cada serviço. | E7: Compare o preço calculado com o preço praticado na sua região.
A9: LEGENDA RÁPIDA
A10: DIGITE AQUI | C10: RESULTADO | E10: ATENÇÃO
A11: Células rosadas | C11: Células verdes | E11: Células amarelas
A13: ANTES DE COMEÇAR
A14: • A planilha não substitui análise contábil, tributária ou de mercado.
A15: • Preço final deve considerar impostos, capacidade, posicionamento e realidade local.
A17: AVISO IMPORTANTE
A18: Material educativo. Adapte à realidade da sua barbearia e valide decisões contábeis, fiscais, trabalhistas e jurídicas com profissionais habilitados.
A19: flowo.com.br/recursos/materiais

Sheet Painel rápido
A1: FLOWO · RESUMO SIMPLES
A2: Seu preço precisa caber na rotina
A3: Use o cálculo como referência e compare com mercado, posicionamento e capacidade.
A5: SERVIÇOS PREENCHIDOS | D5: PREÇO CALCULADO MÉDIO | G5: PREÇOS FINAIS DEFINIDOS
A6: =COUNTIF(Precificação!$A$2:$A$21,"<>") -> 5 | D6: =IFERROR(AVERAGEIF(Precificação!$G$2:$G$21,">0"),0) -> 69.375 | G6: =COUNTIF(Precificação!$H$2:$H$21,">0") -> 0
A7: serviços com nome | D7: referência dos serviços cadastrados | G7: decisões já registradas
A10: PRÓXIMA AÇÃO
A11: Comece por um único serviço: preencha tempo, material usado e margem; depois registre o preço final que faz sentido.
A14: COMO LER
A15: 1. Preencha as células rosadas nas outras abas.
A16: 2. Volte aqui para conferir os números principais.
A17: 3. Resolva primeiro o que estiver pendente ou bloqueado.

Sheet Custos
A1: CUSTOS FIXOS MENSAIS | B1: Valor (R$) | C1: Observações
A2: Aluguel e condomínio | B2: 3200 | C2: Exemplo — substitua
A3: Energia, água e internet | B3: 800 | C3: Exemplo — substitua
A4: Sistemas e serviços | B4: 500 | C4: Exemplo — substitua
A5: Folha, pró-labore e encargos | B5: 12000 | C5: Exemplo — valide com contador
A6: Marketing | B6: 700 | C6: Exemplo — substitua
A7: Outros custos fixos | B7: 800 | C7: Exemplo — substitua
A8: TOTAL FIXO | B8: =SUM(B2:B7) -> 18000
A9: Horas produtivas previstas/mês | B9: 320 | C9: Some as horas disponíveis da equipe; evite zero
A10: CUSTO FIXO POR MINUTO PRODUTIVO | B10: =IFERROR(B8/(B9*60),0) -> 0.9375 | C10: Rateio proporcional ao tempo de cada serviço

Sheet Precificação
A1: Serviço | B1: Tempo (min) | C1: Material usado (R$) | D1: Parte dos custos fixos | E1: Custo total | F1: Margem desejada | G1: Preço calculado | H1: Preço final | I1: Observações
A2: Corte | B2: 40 | C2: 0 | D2: =IF(OR(A2="",B2=""),"",Custos!$B$10*B2) -> 37.5 | E2: =IF(A2="","",C2+D2) -> 37.5 | F2: 0.5 | G2: =IFERROR(E2/(1-F2),0) -> 75
A3: Barba | B3: 30 | C3: 0 | D3: =IF(OR(A3="",B3=""),"",Custos!$B$10*B3) -> 28.125 | E3: =IF(A3="","",C3+D3) -> 28.125 | F3: 0.5 | G3: =IFERROR(E3/(1-F3),0) -> 56.25
A4: Corte + barba | B4: 65 | C4: 0 | D4: =IF(OR(A4="",B4=""),"",Custos!$B$10*B4) -> 60.9375 | E4: =IF(A4="","",C4+D4) -> 60.9375 | F4: 0.5 | G4: =IFERROR(E4/(1-F4),0) -> 121.875
A5: Acabamento | B5: 20 | C5: 0 | D5: =IF(OR(A5="",B5=""),"",Custos!$B$10*B5) -> 18.75 | E5: =IF(A5="","",C5+D5) -> 18.75 | F5: 0.5 | G5: =IFERROR(E5/(1-F5),0) -> 37.5
A6: Outro serviço | B6: 30 | C6: 0 | D6: =IF(OR(A6="",B6=""),"",Custos!$B$10*B6) -> 28.125 | E6: =IF(A6="","",C6+D6) -> 28.125 | F6: 0.5 | G6: =IFERROR(E6/(1-F6),0) -> 56.25
C7: 0 | D7: =IF(OR(A7="",B7=""),"",Custos!$B$10*B7) | E7: =IF(A7="","",C7+D7) | G7: =IFERROR(E7/(1-F7),0) -> 0
C8: 0 | D8: =IF(OR(A8="",B8=""),"",Custos!$B$10*B8) | E8: =IF(A8="","",C8+D8) | G8: =IFERROR(E8/(1-F8),0) -> 0
C9: 0 | D9: =IF(OR(A9="",B9=""),"",Custos!$B$10*B9) | E9: =IF(A9="","",C9+D9) | G9: =IFERROR(E9/(1-F9),0) -> 0
C10: 0 | D10: =IF(OR(A10="",B10=""),"",Custos!$B$10*B10) | E10: =IF(A10="","",C10+D10) | G10: =IFERROR(E10/(1-F10),0) -> 0
C11: 0 | D11: =IF(OR(A11="",B11=""),"",Custos!$B$10*B11) | E11: =IF(A11="","",C11+D11) | G11: =IFERROR(E11/(1-F11),0) -> 0
C12: 0 | D12: =IF(OR(A12="",B12=""),"",Custos!$B$10*B12) | E12: =IF(A12="","",C12+D12) | G12: =IFERROR(E12/(1-F12),0) -> 0
C13: 0 | D13: =IF(OR(A13="",B13=""),"",Custos!$B$10*B13) | E13: =IF(A13="","",C13+D13) | G13: =IFERROR(E13/(1-F13),0) -> 0
C14: 0 | D14: =IF(OR(A14="",B14=""),"",Custos!$B$10*B14) | E14: =IF(A14="","",C14+D14) | G14: =IFERROR(E14/(1-F14),0) -> 0
C15: 0 | D15: =IF(OR(A15="",B15=""),"",Custos!$B$10*B15) | E15: =IF(A15="","",C15+D15) | G15: =IFERROR(E15/(1-F15),0) -> 0
C16: 0 | D16: =IF(OR(A16="",B16=""),"",Custos!$B$10*B16) | E16: =IF(A16="","",C16+D16) | G16: =IFERROR(E16/(1-F16),0) -> 0
C17: 0 | D17: =IF(OR(A17="",B17=""),"",Custos!$B$10*B17) | E17: =IF(A17="","",C17+D17) | G17: =IFERROR(E17/(1-F17),0) -> 0
C18: 0 | D18: =IF(OR(A18="",B18=""),"",Custos!$B$10*B18) | E18: =IF(A18="","",C18+D18) | G18: =IFERROR(E18/(1-F18),0) -> 0
... C21: 0 | D21: =IF(OR(A21="",B21=""),"",Custos!$B$10*B21) | E21: =IF(A21="","",C21+D21) | G21: =IFERROR(E21/(1-F21),0) -> 0
