Workbook

Sheet Comece aqui
A1: FLOWO · MATERIAL PRÁTICO
A2: Fluxo de caixa semanal
A3: Registre entradas e saídas e acompanhe o saldo da barbearia por semana.
A4: Veja o resumo na próxima aba. Depois, preencha somente as células rosadas e volte ao resumo para decidir o que fazer.
A6: 01 | C6: 02 | E6: 03
A7: Defina a data inicial, a quantidade de semanas e o saldo inicial na aba Configuração. | C7: Registre cada movimento com data sem horário e selecione Entrada ou Saída. | E7: Confira o resumo semanal e concilie com conta, caixa e meios de recebimento.
A9: LEGENDA RÁPIDA
A10: DIGITE AQUI | C10: RESULTADO | E10: ATENÇÃO
A11: Células rosadas | C11: Células verdes | E11: Células amarelas
A13: ANTES DE COMEÇAR
A14: • Saldo de caixa não é lucro.
A15: • Confira categorias, impostos e valores recebidos com seu contador.
A17: AVISO IMPORTANTE
A18: Material educativo. Adapte à realidade da sua barbearia e valide decisões contábeis, fiscais, trabalhistas e jurídicas com profissionais habilitados.
A19: flowo.com.br/recursos/materiais

Sheet Painel rápido
A1: FLOWO · RESUMO SIMPLES
A2: Seu caixa da semana sem conta de cabeça
A3: Registre cada movimento e confira se o saldo acumulado combina com o caixa real.
A5: LANÇAMENTOS | D5: ENTRADAS NO PERÍODO | G5: SALDO ACUMULADO
A6: =COUNTA(Lançamentos!$A$2:$A$121) -> 4 | D6: =SUM('Resumo semanal'!$B$2:$B$53) -> 2180 | G6: =INDEX('Resumo semanal'!$E$2:$E$53,Configuração!$B$3) -> 1710
A7: entradas e saídas registradas | D7: soma das semanas configuradas | G7: saldo ao fim da última semana
A10: PRÓXIMA AÇÃO
A11: Compare o saldo acumulado com banco, Pix, cartão e dinheiro. Se não bater, confira a semana mais recente.
A14: COMO LER
A15: 1. Preencha as células rosadas nas outras abas.
A16: 2. Volte aqui para conferir os números principais.
A17: 3. Resolva primeiro o que estiver pendente ou bloqueado.

Sheet Configuração
A1: Configuração | B1: Valor | C1: Orientação
A2: Data inicial da primeira semana | B2: 46237 | C2: Use somente a data, sem horário
A3: Quantidade de semanas | B3: 12 | C3: Escolha de 1 a 52
A4: Saldo inicial (R$) | B4: 0 | C4: Saldo antes da primeira semana

Sheet Lançamentos
A1: Data | B1: Descrição | C1: Categoria | D1: Tipo | E1: Forma | F1: Valor (R$) | G1: Responsável | H1: Comprovante/observação
A2: 46237 | B2: Atendimentos | C2: Serviços | D2: Entrada | E2: Pix | F2: 1200 | G2: Gestor
A3: 46238 | B3: Produtos | C3: Estoque | D3: Saída | E3: Pix | F3: 280 | G3: Gestor
A4: 46239 | B4: Atendimentos | C4: Serviços | D4: Entrada | E4: Cartão | F4: 980 | G4: Gestor
A5: 46240 | B5: Energia | C5: Estrutura | D5: Saída | E5: Boleto | F5: 190 | G5: Gestor

Sheet Resumo semanal
A1: Semana iniciada em | B1: Entradas (R$) | C1: Saídas (R$) | D1: Saldo da semana | E1: Saldo acumulado
A2: =IF(ROW()-1<=Configuração!$B$3,Configuração!$B$2+(ROW()-2)*7,"") -> 46237 | B2: =IF(A2="","",SUMIFS(Lançamentos!$F$2:$F$121,Lançamentos!$D$2:$D$121,"Entrada",Lançamentos!$A$2:$A$121,">="&A2,Lançamentos!$A$2:$A$121,"<"&A2+7)) -> 2180 | C2: =IF(A2="","",SUMIFS(Lançamentos!$F$2:$F$121,Lançamentos!$D$2:$D$121,"Saída",Lançamentos!$A$2:$A$121,">="&A2,Lançamentos!$A$2:$A$121,"<"&A2+7)) -> 470 | D2: =IF(A2="","",B2-C2) -> 1710 | E2: =IF(A2="","",Configuração!$B$4+D2) -> 1710
A3: =IF(ROW()-1<=Configuração!$B$3,Configuração!$B$2+(ROW()-2)*7,"") -> 46244 | B3: =IF(A3="","",SUMIFS(Lançamentos!$F$2:$F$121,Lançamentos!$D$2:$D$121,"Entrada",Lançamentos!$A$2:$A$121,">="&A3,Lançamentos!$A$2:$A$121,"<"&A3+7)) -> 0 | C3: =IF(A3="","",SUMIFS(Lançamentos!$F$2:$F$121,Lançamentos!$D$2:$D$121,"Saída",Lançamentos!$A$2:$A$121,">="&A3,Lançamentos!$A$2:$A$121,"<"&A3+7)) -> 0 | D3: =IF(A3="","",B3-C3) -> 0 | E3: =IF(A3="","",E2+D3) -> 1710
A4: =IF(ROW()-1<=Configuração!$B$3,Configuração!$B$2+(ROW()-2)*7,"") -> 46251 | B4: =IF(A4="","",SUMIFS(Lançamentos!$F$2:$F$121,Lançamentos!$D$2:$D$121,"Entrada",Lançamentos!$A$2:$A$121,">="&A4,Lançamentos!$A$2:$A$121,"<"&A4+7)) -> 0 | C4: =IF(A4="","",SUMIFS(Lançamentos!$F$2:$F$121,Lançamentos!$D$2:$D$121,"Saída",Lançamentos!$A$2:$A$121,">="&A4,Lançamentos!$A$2:$A$121,"<"&A4+7)) -> 0 | D4: =IF(A4="","",B4-C4) -> 0 | E4: =IF(A4="","",E3+D4) -> 1710
A5: =IF(ROW()-1<=Configuração!$B$3,Configuração!$B$2+(ROW()-2)*7,"") -> 46258 | B5: =IF(A5="","",SUMIFS(Lançamentos!$F$2:$F$121,Lançamentos!$D$2:$D$121,"Entrada",Lançamentos!$A$2:$A$121,">="&A5,Lançamentos!$A$2:$A$121,"<"&A5+7)) -> 0 | C5: =IF(A5="","",SUMIFS(Lançamentos!$F$2:$F$121,Lançamentos!$D$2:$D$121,"Saída",Lançamentos!$A$2:$A$121,">="&A5,Lançamentos!$A$2:$A$121,"<"&A5+7)) -> 0 | D5: =IF(A5="","",B5-C5) -> 0 | E5: =IF(A5="","",E4+D5) -> 1710
A6: =IF(ROW()-1<=Configuração!$B$3,Configuração!$B$2+(ROW()-2)*7,"") -> 46265 | B6: =IF(A6="","",SUMIFS(Lançamentos!$F$2:$F$121,Lançamentos!$D$2:$D$121,"Entrada",Lançamentos!$A$2:$A$121,">="&A6,Lançamentos!$A$2:$A$121,"<"&A6+7)) -> 0 | C6: =IF(A6="","",SUMIFS(Lançamentos!$F$2:$F$121,Lançamentos!$D$2:$D$121,"Saída",Lançamentos!$A$2:$A$121,">="&A6,Lançamentos!$A$2:$A$121,"<"&A6+7)) -> 0 | D6: =IF(A6="","",B6-C6) -> 0 | E6: =IF(A6="","",E5+D6) -> 1710
A7: =IF(ROW()-1<=Configuração!$B$3,Configuração!$B$2+(ROW()-2)*7,"") -> 46272 | B7: =IF(A7="","",SUMIFS(Lançamentos!$F$2:$F$121,Lançamentos!$D$2:$D$121,"Entrada",Lançamentos!$A$2:$A$121,">="&A7,Lançamentos!$A$2:$A$121,"<"&A7+7)) -> 0 | C7: =IF(A7="","",SUMIFS(Lançamentos!$F$2:$F$121,Lançamentos!$D$2:$D$121,"Saída",Lançamentos!$A$2:$A$121,">="&A7,Lançamentos!$A$2:$A$121,"<"&A7+7)) -> 0 | D7: =IF(A7="","",B7-C7) -> 0 | E7: =IF(A7="","",E6+D7) -> 1710
A8: =IF(ROW()-1<=Configuração!$B$3,Configuração!$B$2+(ROW()-2)*7,"") -> 46279 | B8: =IF(A8="","",SUMIFS(Lançamentos!$F$2:$F$121,Lançamentos!$D$2:$D$121,"Entrada",Lançamentos!$A$2:$A$121,">="&A8,Lançamentos!$A$2:$A$121,"<"&A8+7)) -> 0 | C8: =IF(A8="","",SUMIFS(Lançamentos!$F$2:$F$121,Lançamentos!$D$2:$D$121,"Saída",Lançamentos!$A$2:$A$121,">="&A8,Lançamentos!$A$2:$A$121,"<"&A8+7)) -> 0 | D8: =IF(A8="","",B8-C8) -> 0 | E8: =IF(A8="","",E7+D8) -> 1710
A9: =IF(ROW()-1<=Configuração!$B$3,Configuração!$B$2+(ROW()-2)*7,"") -> 46286 | B9: =IF(A9="","",SUMIFS(Lançamentos!$F$2:$F$121,Lançamentos!$D$2:$D$121,"Entrada",Lançamentos!$A$2:$A$121,">="&A9,Lançamentos!$A$2:$A$121,"<"&A9+7)) -> 0 | C9: =IF(A9="","",SUMIFS(Lançamentos!$F$2:$F$121,Lançamentos!$D$2:$D$121,"Saída",Lançamentos!$A$2:$A$121,">="&A9,Lançamentos!$A$2:$A$121,"<"&A9+7)) -> 0 | D9: =IF(A9="","",B9-C9) -> 0 | E9: =IF(A9="","",E8+D9) -> 1710
A10: =IF(ROW()-1<=Configuração!$B$3,Configuração!$B$2+(ROW()-2)*7,"") -> 46293 | B10: =IF(A10="","",SUMIFS(Lançamentos!$F$2:$F$121,Lançamentos!$D$2:$D$121,"Entrada",Lançamentos!$A$2:$A$121,">="&A10,Lançamentos!$A$2:$A$121,"<"&A10+7)) -> 0 | C10: =IF(A10="","",SUMIFS(Lançamentos!$F$2:$F$121,Lançamentos!$D$2:$D$121,"Saída",Lançamentos!$A$2:$A$121,">="&A10,Lançamentos!$A$2:$A$121,"<"&A10+7)) -> 0 | D10: =IF(A10="","",B10-C10) -> 0 | E10: =IF(A10="","",E9+D10) -> 1710
A11: =IF(ROW()-1<=Configuração!$B$3,Configuração!$B$2+(ROW()-2)*7,"") -> 46300 | B11: =IF(A11="","",SUMIFS(Lançamentos!$F$2:$F$121,Lançamentos!$D$2:$D$121,"Entrada",Lançamentos!$A$2:$A$121,">="&A11,Lançamentos!$A$2:$A$121,"<"&A11+7)) -> 0 | C11: =IF(A11="","",SUMIFS(Lançamentos!$F$2:$F$121,Lançamentos!$D$2:$D$121,"Saída",Lançamentos!$A$2:$A$121,">="&A11,Lançamentos!$A$2:$A$121,"<"&A11+7)) -> 0 | D11: =IF(A11="","",B11-C11) -> 0 | E11: =IF(A11="","",E10+D11) -> 1710
A12: =IF(ROW()-1<=Configuração!$B$3,Configuração!$B$2+(ROW()-2)*7,"") -> 46307 | B12: =IF(A12="","",SUMIFS(Lançamentos!$F$2:$F$121,Lançamentos!$D$2:$D$121,"Entrada",Lançamentos!$A$2:$A$121,">="&A12,Lançamentos!$A$2:$A$121,"<"&A12+7)) -> 0 | C12: =IF(A12="","",SUMIFS(Lançamentos!$F$2:$F$121,Lançamentos!$D$2:$D$121,"Saída",Lançamentos!$A$2:$A$121,">="&A12,Lançamentos!$A$2:$A$121,"<"&A12+7)) -> 0 | D12: =IF(A12="","",B12-C12) -> 0 | E12: =IF(A12="","",E11+D12) -> 1710
A13: =IF(ROW()-1<=Configuração!$B$3,Configuração!$B$2+(ROW()-2)*7,"") -> 46314 | B13: =IF(A13="","",SUMIFS(Lançamentos!$F$2:$F$121,Lançamentos!$D$2:$D$121,"Entrada",Lançamentos!$A$2:$A$121,">="&A13,Lançamentos!$A$2:$A$121,"<"&A13+7)) -> 0 | C13: =IF(A13="","",SUMIFS(Lançamentos!$F$2:$F$121,Lançamentos!$D$2:$D$121,"Saída",Lançamentos!$A$2:$A$121,">="&A13,Lançamentos!$A$2:$A$121,"<"&A13+7)) -> 0 | D13: =IF(A13="","",B13-C13) -> 0 | E13: =IF(A13="","",E12+D13) -> 1710
A14: =IF(ROW()-1<=Configuração!$B$3,Configuração!$B$2+(ROW()-2)*7,"") | B14: =IF(A14="","",SUMIFS(Lançamentos!$F$2:$F$121,Lançamentos!$D$2:$D$121,"Entrada",Lançamentos!$A$2:$A$121,">="&A14,Lançamentos!$A$2:$A$121,"<"&A14+7)) | C14: =IF(A14="","",SUMIFS(Lançamentos!$F$2:$F$121,Lançamentos!$D$2:$D$121,"Saída",Lançamentos!$A$2:$A$121,">="&A14,Lançamentos!$A$2:$A$121,"<"&A14+7)) | D14: =IF(A14="","",B14-C14) | E14: =IF(A14="","",E13+D14)
... A53: =IF(ROW()-1<=Configuração!$B$3,Configuração!$B$2+(ROW()-2)*7,"") | B53: =IF(A53="","",SUMIFS(Lançamentos!$F$2:$F$121,Lançamentos!$D$2:$D$121,"Entrada",Lançamentos!$A$2:$A$121,">="&A53,Lançamentos!$A$2:$A$121,"<"&A53+7)) | C53: =IF(A53="","",SUMIFS(Lançamentos!$F$2:$F$121,Lançamentos!$D$2:$D$121,"Saída",Lançamentos!$A$2:$A$121,">="&A53,Lançamentos!$A$2:$A$121,"<"&A53+7)) | D53: =IF(A53="","",B53-C53) | E53: =IF(A53="","",E52+D53)
